ackermann/__init__.py
ackermann/__main__.py
ackermann/command.py
ackermann/config.py
ackermann/exceptions.py
ackermann/kahn.py
ackermann/logger.py
ackermann/vars.py
ackermann/test/__init__.py
ackermann/test/test_config.py
ackermann/test/test_kahn.py
ackermann/test/test_units.py
ackermann/units/__init__.py
ackermann/units/argparse.py
ackermann/units/base.py
ackermann/units/command.py
ackermann/units/config.py
ackermann/units/logging.py
ackermann/units/systemd.py
ackermann/units/vars.py
command/__init__.py
command/__main__.py
command/command.py
command/config.py
command/exceptions.py
command/kahn.py
command/logger.py
command/units.py
command/vars.py
command/test/__init__.py
command/test/test_config.py
command/test/test_kahn.py
command/test/test_units.py
command/units/__init__.py
command/units/argparse.py
command/units/base.py
command/units/command.py
command/units/config.py
command/units/logging.py
command/units/systemd.py
command/units/vars.py
test/__init__.py
test/test_config.py
test/test_kahn.py
test/test_units.py
units/__init__.py
units/argparse.py
units/base.py
units/command.py
units/config.py
units/logging.py
units/systemd.py
units/vars.py
ackermann-1.0.0.dist-info/LICENSE
ackermann-1.0.0.dist-info/METADATA
ackermann-1.0.0.dist-info/WHEEL
ackermann-1.0.0.dist-info/top_level.txt
ackermann-1.0.0.dist-info/RECORD
