Metadata-Version: 2.1
Name: ackermann
Version: 1.0.0
Summary: A project cli command and config library
Home-page: https://github.com/baldulin/ackermann
Author: baldulin
Author-email: baldulin@systemli.org
License: UNKNOWN
Project-URL: Bug Tracker, https://github.com/baldulin/ackermann
Platform: UNKNOWN
Classifier: Programming Language :: Python :: 3
Classifier: License :: OSI Approved :: MIT License
Classifier: Operating System :: OS Independent
Requires-Python: >=3.6
License-File: LICENSE
Provides-Extra: systemd
Requires-Dist: systemd-python ; extra == 'systemd'
